beamlogger.py
BeamLogger/__init__.py
BeamLogger/beamlogger.py
BeamLogger-0.1.5.dist-info/LICENSE
BeamLogger-0.1.5.dist-info/METADATA
BeamLogger-0.1.5.dist-info/WHEEL
BeamLogger-0.1.5.dist-info/top_level.txt
BeamLogger-0.1.5.dist-info/RECORD
