Metadata-Version: 2.1
Name: BeamLogger
Version: 0.1.5
Summary: A stylish and colorful Python logging module with customizable console output
Home-page: https://github.com/bhaskarsaikia-17/BeamLogger
Author: Bhaskar
Author-email: toolscord.supp@gmail.com
Classifier: Programming Language :: Python :: 3
Classifier: License :: OSI Approved :: MIT License
Classifier: Operating System :: OS Independent
Requires-Python: >=3.6
License-File: LICENSE
Requires-Dist: colorama
Requires-Dist: pystyle
